[
    {
        "nome": "Angelo Marconi Pavan",
        "funcao": "Membro",
        "descricao": "Membro da inciativa eVTOL",
        "rosto": "/assets/img/rostos/pavan.jpeg",
        "linkedin": "https://www.linkedin.com/in/%C3%A2ngelo-pavan-691420161/"
    },
    {
        "nome": "Gabriel Juliatti Costalonga",
        "funcao": "Membro",
        "descricao": "Conhecido na comunidade iteana como Libras, tenho 22 anos e sou natural de Vila Velha - ES. Com espírito leve e aventureiro, estou sempre disposto a experimentar coisas novas e buscar desenvolver novas habilidades. Nos tempos livres, tomar uma gelada é sempre a melhor opção!",
        "rosto": "/assets/img/rostos/juliatti.png",
        "linkedin": "https://www.linkedin.com/in/%C3%A2ngelo-pavan-691420161/"
    }
]